{"url": "/m/once/", "isOnOpening": false, "boxoffice": "$9.2M", "genreSet": [{"displayName": "Musical & Performing Arts", "id": 12}, {"displayName": "Drama", "id": 9}], "officialUrl": "http://www.foxsearchlight.com/once/", "isInTheaters": false, "synopsis": "\"Once\" is a modern-day musical set on the streets of Dublin. Featuring Glen Hansard and his Irish band The Frames, \"Once\" tells the story of a street musician and a Czech immigrant during an eventful week as they write, rehearse and record songs that reveal their unique love story.", "links": {"alternate": "//www.rottentomatoes.com/m/once/"}, "runningTime": 86, "year": 2007, "trackingType": "DvdOther", "status": "Live", "isPlaying": false, "isOnDVD": true, "runningTimeStr": "1 hr. 26 min.", "ratingSummary": {"topcount": 55, "consensus": "A charming, captivating tale of love and music, Once sets the standard for the modern musical. And with Dublin as its backdrop, Once is fun and fresh.", "topCritics": {"hasScore": true, "numReviews": 55, "meterClass": "certified", "numRotten": 0, "numFresh": 55, "hasReviews": true, "meterValue": 100, "averageRating": 8.301455}, "audience": {"meterScore": 91, "averageScore": 4.05659294128418, "numTotal": 191007, "ratingType": "viewed"}, "allcount": 158, "rottencount": 5, "dvdcount": 11, "allCritics": {"hasScore": true, "numReviews": 158, "meterClass": "certified", "numRotten": 5, "numFresh": 153, "hasReviews": true, "meterValue": 97, "averageRating": 8.3}, "freshcount": 153}, "mpaaRating": "R", "vanity": "once", "photos": {"photos": [{"url": "https://resizing.flixster.com/oWyxdRmK8XVFlWhvEwyIVkO4muY=/655x477/v1.bjsyNjQ2Njk7ajsxODc5MjsyMDQ4OzY1NTs0Nzc", "index": 0, "submittedBy": "RT Staff", "height": 477, "imageId": 264669, "thumbnail": "https://resizing.flixster.com/6PAQ-banXwaq2rFNTWFHEnRlPpQ=/80x80/v1.bjsyNjQ2Njk7ajsxODc5MjsyMDQ4OzY1NTs0Nzc", "submittedDate": "2014-07-03", "id": "multiuse-264669", "photoType": "movie", "width": 655}, {"url": "https://resizing.flixster.com/t9Zvuy7x9i2Kw4VrML-_NN0asd4=/656x438/v1.bjsyNjQ2NzA7ajsxODc5MzsyMDQ4OzY1Njs0Mzg", "index": 1, "submittedBy": "RT Staff", "height": 438, "imageId": 264670, "thumbnail": "https://resizing.flixster.com/HfFoXh4R87LxYWRvKTY-nlaKuWc=/80x80/v1.bjsyNjQ2NzA7ajsxODc5MzsyMDQ4OzY1Njs0Mzg", "submittedDate": "2014-07-03", "id": "multiuse-264670", "photoType": "movie", "width": 656}, {"url": "https://resizing.flixster.com/r77CjH0zm6Tvz7pBOEJTrSmHSKM=/664x458/v1.bjsyNjQ2NzE7ajsxODc5NDsyMDQ4OzY2NDs0NTg", "index": 2, "submittedBy": "RT Staff", "height": 458, "imageId": 264671, "thumbnail": "https://resizing.flixster.com/XWNjViTFuNgqqiNouQuLwAXFrOQ=/80x80/v1.bjsyNjQ2NzE7ajsxODc5NDsyMDQ4OzY2NDs0NTg", "submittedDate": "2014-07-03", "id": "multiuse-264671", "photoType": "movie", "width": 664}, {"url": "https://resizing.flixster.com/BLSTJ_OoLxlKwoi22Uoo41gFzOs=/665x471/v1.bjsyNjQ2NzI7ajsxODc5NTsyMDQ4OzY2NTs0NzE", "index": 3, "submittedBy": "RT Staff", "height": 471, "imageId": 264672, "thumbnail": "https://resizing.flixster.com/wACN9raZK9CC-FxtxRFMu0h7DJk=/80x80/v1.bjsyNjQ2NzI7ajsxODc5NTsyMDQ4OzY2NTs0NzE", "submittedDate": "2014-07-03", "id": "multiuse-264672", "photoType": "movie", "width": 665}, {"url": "https://resizing.flixster.com/dWVRvwIzh85ee0AUMY2kNY4IctQ=/366x479/v1.bjsyNjQ2NzM7ajsxODc5NjsyMDQ4OzM2Njs0Nzk", "index": 4, "submittedBy": "RT Staff", "height": 479, "imageId": 264673, "thumbnail": "https://resizing.flixster.com/jfJJEZVQ4oivJz58REG8I9XL6z8=/80x80/v1.bjsyNjQ2NzM7ajsxODc5NjsyMDQ4OzM2Njs0Nzk", "submittedDate": "2014-07-03", "id": "multiuse-264673", "photoType": "movie", "width": 366}, {"url": "https://resizing.flixster.com/uYSECO1qyU5aOFMMje1HvC9xNdg=/661x479/v1.bjsyNjQ2NzQ7ajsxODc5NzsyMDQ4OzY2MTs0Nzk", "index": 5, "submittedBy": "RT Staff", "height": 479, "imageId": 264674, "thumbnail": "https://resizing.flixster.com/pndIE9vjWjNFKMpNyUfF_IeAnZU=/80x80/v1.bjsyNjQ2NzQ7ajsxODc5NzsyMDQ4OzY2MTs0Nzk", "submittedDate": "2014-07-03", "id": "multiuse-264674", "photoType": "movie", "width": 661}, {"url": "https://resizing.flixster.com/i0mhnwBoeOlh0us18yq9ObfZ0bU=/300x200/v1.bjsyNjQ2NzU7ajsxODc5ODsyMDQ4OzMwMDsyMDA", "index": 6, "submittedBy": "RT Staff", "height": 200, "imageId": 264675, "thumbnail": "https://resizing.flixster.com/9CdslFaHpufCy2MWoQBpt0jHgjw=/80x80/v1.bjsyNjQ2NzU7ajsxODc5ODsyMDQ4OzMwMDsyMDA", "submittedDate": "2014-07-03", "id": "multiuse-264675", "photoType": "movie", "width": 300}, {"url": "https://resizing.flixster.com/79HO8zgcv4hyZc--fM2gSxiv_RU=/300x200/v1.bjsyNjQ2NzY7ajsxODc5OTsyMDQ4OzMwMDsyMDA", "index": 7, "submittedBy": "RT Staff", "height": 200, "imageId": 264676, "thumbnail": "https://resizing.flixster.com/SJfaHN-ewhFoQpF2t8jgS513bCQ=/80x80/v1.bjsyNjQ2NzY7ajsxODc5OTsyMDQ4OzMwMDsyMDA", "submittedDate": "2014-07-03", "id": "multiuse-264676", "photoType": "movie", "width": 300}, {"url": "https://resizing.flixster.com/eKVQuO_aen3lzves3MwZHw-YL5k=/997x1024/v1.bjsyNTc0MTIxO2o7MTg4NzA7MjA0ODszMDAwOzMwODA", "index": 8, "submittedBy": "RT Staff", "height": 1024, "imageId": 2574121, "thumbnail": "https://resizing.flixster.com/x5saklTcdjFK8gHlnj3j4tVyviI=/80x80/v1.bjsyNTc0MTIxO2o7MTg4NzA7MjA0ODszMDAwOzMwODA", "submittedDate": "2020-08-03", "id": "multiuse-2574121", "photoType": "movie", "width": 997}, {"url": "https://resizing.flixster.com/0PCQu-ShJ5Im-Haph22CTsRW4Dg=/378x600/v1.aDsyNzUzNjtqOzE4ODA2OzIwNDg7NDQxOzcwMA", "index": 9, "submittedBy": "RT Staff", "height": 600, "imageId": 27536, "thumbnail": "https://resizing.flixster.com/ULNIt5c8cCNIoMMVsr-ptEvUn_Q=/80x80/v1.aDsyNzUzNjtqOzE4ODA2OzIwNDg7NDQxOzcwMA", "submittedDate": "2010-03-29", "id": "movie-27536", "photoType": "movie", "width": 378}, {"url": "https://resizing.flixster.com/CKwoXAdmVdlklVZjPqhwxO7uFFM=/423x600/v1.aDsyNTgxMDtqOzE4NzkwOzIwNDg7NDkzOzcwMA", "index": 10, "submittedBy": "RT Staff", "height": 600, "imageId": 25810, "thumbnail": "https://resizing.flixster.com/Bryy8wNcXMr0QolJEI8IhZJSHT8=/80x80/v1.aDsyNTgxMDtqOzE4NzkwOzIwNDg7NDkzOzcwMA", "submittedDate": "2010-03-29", "id": "movie-25810", "photoType": "movie", "width": 423}, {"url": "https://resizing.flixster.com/GOFrxbm1ISgpGeSLiwf2jL6rM68=/514x599/v1.aDsyMzk0MDtqOzE4NzY1OzIwNDg7NjAwOzcwMA", "index": 11, "submittedBy": "RT Staff", "height": 599, "imageId": 23940, "thumbnail": "https://resizing.flixster.com/llMb5LNTOknwsN07HhnT50R7X1c=/80x80/v1.aDsyMzk0MDtqOzE4NzY1OzIwNDg7NjAwOzcwMA", "submittedDate": "2010-03-29", "id": "movie-23940", "photoType": "movie", "width": 514}, {"url": "https://resizing.flixster.com/5A1XDyOUL676ErYJKymXNuuJflU=/465x600/v1.aDsyMTkxMTtqOzE4ODA2OzIwNDg7NTQyOzcwMA", "index": 12, "submittedBy": "RT Staff", "height": 600, "imageId": 21911, "thumbnail": "https://resizing.flixster.com/O7zho-E69iZLwv4AEIpA35-qlzE=/80x80/v1.aDsyMTkxMTtqOzE4ODA2OzIwNDg7NTQyOzcwMA", "submittedDate": "2010-03-29", "id": "movie-21911", "photoType": "movie", "width": 465}, {"url": "https://resizing.flixster.com/PU6cE6T_vTsEinpARR4GqVVXb34=/420x600/v1.aDsxOTY5MDtqOzE4NzkwOzIwNDg7NDkwOzcwMA", "index": 13, "submittedBy": "RT Staff", "height": 600, "imageId": 19690, "thumbnail": "https://resizing.flixster.com/l9qIRC2pd1ooW4atbUyLp_xFCwA=/80x80/v1.aDsxOTY5MDtqOzE4NzkwOzIwNDg7NDkwOzcwMA", "submittedDate": "2010-03-29", "id": "movie-19690", "photoType": "movie", "width": 420}, {"url": "https://resizing.flixster.com/AioHmnvcMp3bpm2oXXiitOMCOqE=/600x431/v1.aDsxNzI1MjtqOzE4NzgyOzIwNDg7NzAwOzUwMw", "index": 14, "submittedBy": "RT Staff", "height": 431, "imageId": 17252, "thumbnail": "https://resizing.flixster.com/Y7_hWZzCDS78f_rPakCkJF_VZrA=/80x80/v1.aDsxNzI1MjtqOzE4NzgyOzIwNDg7NzAwOzUwMw", "submittedDate": "2010-03-29", "id": "movie-17252", "photoType": "movie", "width": 600}, {"url": "https://resizing.flixster.com/EA53G_68B0Hr6d8wnAqg83Wn754=/600x325/v1.aDsxNDU1MTtqOzE4NzgxOzIwNDg7NzAwOzM3OQ", "index": 15, "submittedBy": "RT Staff", "height": 325, "imageId": 14551, "thumbnail": "https://resizing.flixster.com/pmZx2-64EpnhK59VLviQ0uv8dNQ=/80x80/v1.aDsxNDU1MTtqOzE4NzgxOzIwNDg7NzAwOzM3OQ", "submittedDate": "2010-03-29", "id": "movie-14551", "photoType": "movie", "width": 600}, {"url": "https://resizing.flixster.com/7CoX14xPga5cULcmXvq2utLGyuw=/600x375/v1.aDsxMTYxOTtqOzE4Nzc0OzIwNDg7NzAwOzQzNw", "index": 16, "submittedBy": "RT Staff", "height": 375, "imageId": 11619, "thumbnail": "https://resizing.flixster.com/hx7mA6ct1P9DfAGyYrLYvp0xRKo=/80x80/v1.aDsxMTYxOTtqOzE4Nzc0OzIwNDg7NzAwOzQzNw", "submittedDate": "2010-03-29", "id": "movie-11619", "photoType": "movie", "width": 600}, {"url": "https://resizing.flixster.com/tWmimzfE8Cqk9phPa-Gww9VRJrw=/600x475/v1.aDs4NTE0O2o7MTg3NzQ7MjA0ODs3MDA7NTU0", "index": 17, "submittedBy": "RT Staff", "height": 475, "imageId": 8514, "thumbnail": "https://resizing.flixster.com/zjkortIKCh4b3ZMBqLEZb6GaK6o=/80x80/v1.aDs4NTE0O2o7MTg3NzQ7MjA0ODs3MDA7NTU0", "submittedDate": "2010-03-29", "id": "movie-8514", "photoType": "movie", "width": 600}, {"url": "https://resizing.flixster.com/RCKBbqISpK5iOC3b4tceaxiVrOA=/401x600/v1.aDs1Mjc5O2o7MTg3Nzk7MjA0ODs0Njg7NzAw", "index": 18, "submittedBy": "RT Staff", "height": 600, "imageId": 5279, "thumbnail": "https://resizing.flixster.com/_cdQFYN9m5y3kTIpddQCdoG5IAU=/80x80/v1.aDs1Mjc5O2o7MTg3Nzk7MjA0ODs0Njg7NzAw", "submittedDate": "2010-03-29", "id": "movie-5279", "photoType": "movie", "width": 401}, {"url": "https://resizing.flixster.com/9WNhCZgSEsdt3kKBN_Ojr4H1ZD0=/347x215/v1.aDsxOTA3O2o7MTg3ODI7MjA0ODszNDc7MjE1", "index": 19, "submittedBy": "RT Staff", "height": 215, "imageId": 1907, "thumbnail": "https://resizing.flixster.com/ejzxz6G9obFKevtpcC4DlyFMZ38=/80x80/v1.aDsxOTA3O2o7MTg3ODI7MjA0ODszNDc7MjE1", "submittedDate": "2010-03-29", "id": "movie-1907", "photoType": "movie", "width": 347}], "length": 20}, "studio": "Fox Searchlight", "purchaseOptions": {"amazon": {"url": "http://www.amazon.com/gp/product/B003YTLKTE/ref=atv_feed_catalog?tag=rottetomao_aiv_mv-20", "isPrime": false, "type": "rent"}, "vudu": {"url": "https://www.vudu.com/content/movies/details/Once/129019", "type": "buy"}, "flixster": {"url": "once", "movieId": "ID: 2000070321; SKU:489199; Type: B (SD Buy)", "type": "buy"}, "iTunes": {"url": "https://itunes.apple.com/movie/once/id270012018?uo=5", "price": "14.99"}}, "reviews": {"total": 158, "links": {"alternate": "//www.rottentomatoes.com/m/once/#reviews", "self": "api.flixster.com/movies/once/reviews.json?review_type=mob&country=us&page=1", "prev": "api.flixster.com/movies/once/reviews.json?review_type=mob&country=us&page=0", "next": "api.flixster.com/movies/once/reviews.json?review_type=mob&country=us&page=2"}, "reviews": [{"isRotten": false, "url": "http://www.decentfilms.com/sections/reviews/2787", "creationDate": 1225275343000, "isFresh": true, "id": 1777185, "quote": "At once delicate and gritty, wistful and deeply satisfying.", "links": {"review": "http://www.decentfilms.com/sections/reviews/2787"}, "publication": {"name": "Decent Films Guide"}, "isTop": true, "freshness": "fresh", "critic": {"url": "/critic/steven-d-greydanus", "name": "Steven D. Greydanus", "id": 5612, "thumbnailImage": "https://resizing.flixster.com/TpXNeP2Bw4Ci0Knwz0ug2Ok6rWw=/72x72/v1.YzsyODA4O2c7MTg3ODM7MjA0ODsxNTA7MTUw"}, "original_score": "A-"}, {"isRotten": false, "url": "http://www.npr.org/templates/story/story.php?storyId=10256223", "publication": {"name": "NPR.org"}, "isTop": true, "creationDate": 1224341334000, "isFresh": true, "freshness": "fresh", "critic": {"url": "/critic/bob-mondello", "name": "Bob Mondello", "id": 13070, "thumbnailImage": "https://resizing.flixster.com/EL1cvDHU4A1tZT0n1ygIUVWqXwI=/72x72/v1.YzsxODEzO2c7MTg3Nzg7MjA0ODszODs0Mg"}, "quote": "So this is how you make a low-budget musical these days!", "id": 1771665, "links": {"review": "http://www.npr.org/templates/story/story.php?storyId=10256223"}}, {"isRotten": false, "url": "http://www.tnr.com/booksarts/story.html?id=bc84adfd-bf7c-4c10-8e67-a9793154b90c", "publication": {"url": "", "name": "The New Republic"}, "isTop": true, "creationDate": 1221795760000, "isFresh": true, "freshness": "fresh", "critic": {"url": "/critic/christopher-orr", "name": "Christopher Orr", "id": 10572, "thumbnailImage": "https://resizing.flixster.com/HH6eGkwVnVin9zTitk1Sgn1fDh4=/72x72/v1.YzsyNTk5O2c7MTg3OTk7MjA0ODsxNTA7MTUw"}, "quote": "In an era when Hollywood has largely lost the ability to distinguish between romance and sex, Once is the rare film that recognizes that love is no less love for being held in check, it is merely a different kind of love.", "id": 1757151, "links": {"review": "http://www.tnr.com/booksarts/story.html?id=bc84adfd-bf7c-4c10-8e67-a9793154b90c"}}, {"isRotten": false, "url": "http://www.film.com/dvds/story/onceworthseeingtwicethreetimesorfour/11597476/17720685", "publication": {"url": "", "name": "Film.com"}, "isTop": true, "creationDate": 1198121427000, "isFresh": true, "freshness": "fresh", "critic": {"url": "/critic/mark-bourne", "name": "Mark Bourne", "id": 12017, "thumbnailImage": "https://resizing.flixster.com/HE84wKaGB6WC5yWqHDluK7-tvRA=/72x72/v1.YzsxNzkxO2o7MTg4MDE7MjA0ODszODs0Mw"}, "quote": "Once doesn't plop its emotions on its characters' sleeves, and it trusts us enough to leave some of the best stuff unstated. In other words, it trusts us to know that half the music lies between the notes.", "id": 1698302, "links": {"review": "http://www.film.com/dvds/story/onceworthseeingtwicethreetimesorfour/11597476/17720685"}}, {"isRotten": false, "url": "http://www.littlewhite lies.co.uk", "publication": {"url": "", "name": "Little White Lies"}, "isTop": true, "creationDate": 1192812222000, "isFresh": true, "freshness": "fresh", "quote": "A simply sung tale that deserves attention.", "id": 1681452, "original_score": "4/5", "links": {"review": "http://www.littlewhite lies.co.uk"}}, {"isRotten": false, "url": "http://www.telegraph.co.uk/arts/main.jhtml?xml=/arts/2007/10/19/bfrendition1.xml&page=2", "publication": {"url": "", "name": "Daily Telegraph (UK)"}, "isTop": true, "creationDate": 1192811986000, "isFresh": true, "freshness": "fresh", "critic": {"url": "/critic/sukhdev-sandhu", "name": "Sukhdev Sandhu", "id": 12413, "thumbnailImage": "https://d2a5cgar23scu2.cloudfront.net/static/images/redesign/user.none.tmb.jpg"}, "quote": "Not since Before Sunset has a romantic film managed to be as touching, funny or as hard to forget as Once.", "id": 1681447, "links": {"review": "http://www.telegraph.co.uk/arts/main.jhtml?xml=/arts/2007/10/19/bfrendition1.xml&page=2"}}, {"isRotten": false, "url": "https://theindependentcritic.com/once", "creationDate": 1600456499000, "isFresh": true, "id": 2726266, "quote": "A simple miracle of a film.", "links": {"review": "https://theindependentcritic.com/once"}, "publication": {"url": "", "name": "TheIndependentCritic.com"}, "isTop": false, "freshness": "fresh", "critic": {"url": "/critic/richard-propes-27470", "name": "Richard Propes", "id": 27470, "thumbnailImage": "https://resizing.flixster.com/9RafzdrYTvTWxFzPswX4QYwPgK8=/72x72/v1.YzszODAzO2o7MTg3ODg7MjA0ODszMDA7MzAw"}, "original_score": "4.0/4.0"}, {"isRotten": false, "url": "https://www.the-dispatch.com/news/20070816/irish-musical-is-a-unique-love-story", "creationDate": 1559794197000, "isFresh": true, "id": 2594423, "quote": "Movies like this don't come along very often, and Once is really something special.", "links": {"review": "https://www.the-dispatch.com/news/20070816/irish-musical-is-a-unique-love-story"}, "publication": {"url": "", "name": "The Dispatch (Lexington, NC)"}, "isTop": false, "freshness": "fresh", "critic": {"url": "/critic/matthew-lucas", "name": "Matthew Lucas", "id": 25079, "thumbnailImage": "https://resizing.flixster.com/hC9DIwh8TBZinZWNombChPlC53Y=/72x72/v1.YzszMzgzO2o7MTg3NzM7MjA0ODszMDA7MzAw"}, "original_score": "4/4"}, {"isRotten": false, "url": "https://newsok.com/article/3077267/once-seen-the-love-story-in-this-unusual-musical-stays-with-you", "creationDate": 1534294365000, "isFresh": true, "id": 2497660, "quote": "The simple and real love story will stay with you.", "links": {"review": "https://newsok.com/article/3077267/once-seen-the-love-story-in-this-unusual-musical-stays-with-you"}, "publication": {"url": "", "name": "The Oklahoman"}, "isTop": false, "freshness": "fresh", "critic": {"url": "/critic/brandy-mcdonnell", "name": "Brandy McDonnell", "id": 18824, "thumbnailImage": "https://resizing.flixster.com/vSOxJMGxnDpzZDl9xVY0Oc2wsYs=/72x72/v1.YzszMDM0O2c7MTg3ODQ7MjA0ODsxNTA7MTUw"}, "original_score": "3.5/4"}, {"isRotten": false, "url": "http://moviemet.com/review/once-blu-ray-review", "creationDate": 1397824903000, "isFresh": true, "id": 2198501, "quote": "If \"The Commitments\" shows the gritty, robust side of Dublin and the Irish music scene, \"Once\" shows us a softer, more romantic side.", "links": {"review": "http://moviemet.com/review/once-blu-ray-review"}, "publication": {"url": "", "name": "Movie Metropolis"}, "isTop": false, "freshness": "fresh", "critic": {"url": "/critic/james-plath", "name": "James Plath", "id": 8011, "thumbnailImage": "https://resizing.flixster.com/lb9VzfnffMFSUjoDkNs0nZpuK4w=/72x72/v1.YzsxNzUxO2c7MTg4MDY7MjA0ODszODs0Mg"}, "original_score": "8/10"}, {"isRotten": false, "url": "http://www.bullz-eye.com/mguide/reviews_2007/once.htm", "creationDate": 1224341333000, "isFresh": true, "id": 1771664, "quote": "There is much to admire about Once, in a little-movie-that-could kind of way, but it can't help but get in its own way just when it begins to gain some momentum", "links": {"review": "http://www.bullz-eye.com/mguide/reviews_2007/once.htm"}, "publication": {"url": "", "name": "Bullz-Eye.com"}, "isTop": false, "freshness": "fresh", "critic": {"url": "/critic/david-medsker", "name": "David Medsker", "id": 12750, "thumbnailImage": "https://d2a5cgar23scu2.cloudfront.net/static/images/redesign/user.none.tmb.jpg"}, "original_score": "3.5/5"}, {"isRotten": true, "url": "http://www.7mpictures.com/once-dvd-review/", "creationDate": 1219035404000, "isFresh": false, "id": 1749850, "quote": "my biggest road block was the fact that I didn't like the music", "links": {"review": "http://www.7mpictures.com/once-dvd-review/"}, "publication": {"name": "7M Pictures"}, "isTop": false, "freshness": "rotten", "critic": {"url": "/critic/kevin-carr", "name": "Kevin Carr", "id": 6773, "thumbnailImage": "https://resizing.flixster.com/O5khATpi-cDaFtSz1l_XATBIORI=/72x72/v1.YzsxNzQ3O2o7MTg4MDI7MjA0ODszODs1NA"}, "original_score": "2/5"}]}, "casts": {"screenwriters": [{"url": "/celebrity/john_carney/", "name": "John Carney", "thumbnailImg": "https://resizing.flixster.com/XKhIfPPoAB41vEWYYROSUkM8IWo=/80x80/v1.cDs2ODIzNzgxO2o7MTg4Njk7MjA0ODsxOTUwOzI3Mjg"}], "directors": [{"url": "/celebrity/john_carney/", "name": "John Carney", "thumbnailImg": "https://resizing.flixster.com/XKhIfPPoAB41vEWYYROSUkM8IWo=/80x80/v1.cDs2ODIzNzgxO2o7MTg4Njk7MjA0ODsxOTUwOzI3Mjg"}], "creators": [], "producers": [{"url": "/celebrity/martina-niland/", "name": "Martina Niland", "thumbnailImg": "https://d2a5cgar23scu2.cloudfront.net/static/images/redesign/actor.default.tmb.gif"}, {"url": "/celebrity/david_collins/", "name": "David Collins", "thumbnailImg": "https://resizing.flixster.com/5TapWwLzQgqLC_Vk6J_JksqWWIQ=/80x80/v1.cjsxOTk2MjtqOzE4NzkyOzIwNDg7NDY2OzY1Mg"}], "castItems": [{"person": {"url": "/celebrity/glen_hansard/", "name": "Glen Hansard", "thumbnailImg": "https://resizing.flixster.com/EkFOLD-LU1q4f4CaxxovTd7gETs=/80x80/v1.cDs2ODIzNzMwO2o7MTg4NjM7MjA0ODsyMTAwOzI5MjI"}, "characters": [{"name": "Guy"}]}, {"person": {"url": "/celebrity/marketa-irglova/", "name": "Mark\u00e9ta Irglov\u00e1", "thumbnailImg": "https://resizing.flixster.com/B1_pf0WSNdEOfqx2lrB_MA6RV0w=/80x80/v1.cDsxMTAzMDE5MDtqOzE4ODYyOzIwNDg7MjUwOzM1OQ"}, "characters": [{"name": "Girl"}]}, {"person": {"url": "/celebrity/geoff_minogue/", "name": "Geoff Minogue", "thumbnailImg": "https://d2a5cgar23scu2.cloudfront.net/static/images/redesign/actor.default.tmb.gif"}, "characters": [{"name": "Eamon"}]}, {"person": {"url": "/celebrity/mal-whyte/", "name": "Mal Whyte", "thumbnailImg": "https://d2a5cgar23scu2.cloudfront.net/static/images/redesign/actor.default.tmb.gif"}, "characters": [{"name": "Bill"}]}, {"person": {"url": "/celebrity/bill_hodnett/", "name": "Bill Hodnett", "thumbnailImg": "https://d2a5cgar23scu2.cloudfront.net/static/images/redesign/actor.default.tmb.gif"}, "characters": [{"name": "Guy's Dad"}]}, {"person": {"url": "/celebrity/danuse_ktrestova/", "name": "Danuse Ktrestova", "thumbnailImg": "https://d2a5cgar23scu2.cloudfront.net/static/images/redesign/actor.default.tmb.gif"}, "characters": [{"name": "Girl's Mother"}]}, {"person": {"url": "/celebrity/alastair_foley/", "name": "Alastair Foley", "thumbnailImg": "https://d2a5cgar23scu2.cloudfront.net/static/images/redesign/actor.default.tmb.gif"}, "characters": [{"name": "Bassist"}]}, {"person": {"url": "/celebrity/gerard_hendrick/", "name": "Gerard Hendrick", "thumbnailImg": "https://d2a5cgar23scu2.cloudfront.net/static/images/redesign/actor.default.tmb.gif"}, "characters": [{"name": "Lead Guitarist"}]}, {"person": {"url": "/celebrity/darren_healy/", "name": "Darren Healy", "thumbnailImg": "https://resizing.flixster.com/G9C0r9xlCoQCo9E7BIjS8fCL8PY=/80x80/v1.cDsxMTI3ODM0OTtqOzE4ODk0OzIwNDg7NjI2OzQ3NQ"}, "characters": [{"name": "Heroin Addict"}]}, {"person": {"url": "/celebrity/marcella_plunkett/", "name": "Marcella Plunkett", "thumbnailImg": "https://d2a5cgar23scu2.cloudfront.net/static/images/redesign/actor.default.tmb.gif"}, "characters": [{"name": "Ex-Girlfriend"}]}, {"person": {"url": "/celebrity/paul_clarke/", "name": "Paul Clarke", "thumbnailImg": "https://d2a5cgar23scu2.cloudfront.net/static/images/redesign/actor.default.tmb.gif"}, "characters": [{"name": "Shop Assistant"}]}, {"person": {"url": "/celebrity/niall_cleary/", "name": "Niall Cleary", "thumbnailImg": "https://d2a5cgar23scu2.cloudfront.net/static/images/redesign/actor.default.tmb.gif"}, "characters": [{"name": "Bob"}]}, {"person": {"url": "/celebrity/maire_walsh/", "name": "Maire Walsh", "thumbnailImg": "https://d2a5cgar23scu2.cloudfront.net/static/images/redesign/actor.default.tmb.gif"}, "characters": [{"name": "Lady on Bus"}]}, {"person": {"url": "/celebrity/witold_owski/", "name": "Witold Owski", "thumbnailImg": "https://d2a5cgar23scu2.cloudfront.net/static/images/redesign/actor.default.tmb.gif"}, "characters": [{"name": "Man Watching TV"}]}, {"person": {"url": "/celebrity/pat_mcgrath/", "name": "Pat McGrath", "thumbnailImg": "https://d2a5cgar23scu2.cloudfront.net/static/images/redesign/actor.default.tmb.gif"}, "characters": [{"name": "Drunk"}]}, {"person": {"url": "/celebrity/hugh_walsh/", "name": "Hugh Walsh", "thumbnailImg": "https://d2a5cgar23scu2.cloudfront.net/static/images/redesign/actor.default.tmb.gif"}, "characters": [{"name": "Timmy Drummer"}]}, {"person": {"url": "/celebrity/tomek_glowacki/", "name": "Tomek Glowacki", "thumbnailImg": "https://d2a5cgar23scu2.cloudfront.net/static/images/redesign/actor.default.tmb.gif"}, "characters": [{"name": "Man Watching TV"}]}, {"person": {"url": "/celebrity/sean_millar/", "name": "Sean Millar", "thumbnailImg": "https://d2a5cgar23scu2.cloudfront.net/static/images/redesign/actor.default.tmb.gif"}, "characters": [{"name": "Bank Manager"}]}, {"person": {"url": "/celebrity/attila_kouvacs/", "name": "Attila Kouvacs", "thumbnailImg": "https://d2a5cgar23scu2.cloudfront.net/static/images/redesign/actor.default.tmb.gif"}, "characters": [{"name": "Man Watching TV"}]}, {"person": {"url": "/celebrity/pete_short/", "name": "Pete Short", "thumbnailImg": "https://d2a5cgar23scu2.cloudfront.net/static/images/redesign/actor.default.tmb.gif"}, "characters": [{"name": "Singer at Party"}]}, {"person": {"url": "/celebrity/bob_hoban/", "name": "Bob Hoban", "thumbnailImg": "https://d2a5cgar23scu2.cloudfront.net/static/images/redesign/actor.default.tmb.gif"}, "characters": [{"name": "Shop Assistant at Bogarts"}]}, {"person": {"url": "/celebrity/dave_cleary/", "name": "Dave Cleary", "thumbnailImg": "https://d2a5cgar23scu2.cloudfront.net/static/images/redesign/actor.default.tmb.gif"}, "characters": [{"name": "Host at Party"}]}, {"person": {"url": "/celebrity/praghosa/", "name": "Praghosa", "thumbnailImg": "https://d2a5cgar23scu2.cloudfront.net/static/images/redesign/actor.default.tmb.gif"}, "characters": [{"name": "Hari Krishna"}]}, {"person": {"url": "/celebrity/keith_byrne/", "name": "Keith Byrne", "thumbnailImg": "https://d2a5cgar23scu2.cloudfront.net/static/images/redesign/actor.default.tmb.gif"}, "characters": [{"name": "Guy in Piano Shop"}]}, {"person": {"url": "/celebrity/krzysztos_tlotka/", "name": "Krzysztos Tlotka", "thumbnailImg": "https://d2a5cgar23scu2.cloudfront.net/static/images/redesign/actor.default.tmb.gif"}, "characters": [{"name": "Man Watching TV"}]}, {"person": {"url": "/celebrity/kate_haugh/", "name": "Kate Haugh", "thumbnailImg": "https://d2a5cgar23scu2.cloudfront.net/static/images/redesign/actor.default.tmb.gif"}, "characters": [{"name": "Baby"}]}, {"person": {"url": "/celebrity/senan_haugh/", "name": "Senan Haugh", "thumbnailImg": "https://d2a5cgar23scu2.cloudfront.net/static/images/redesign/actor.default.tmb.gif"}, "characters": [{"name": "Husband"}]}, {"person": {"url": "/celebrity/catherine_hansard/", "name": "Catherine Hansard", "thumbnailImg": "https://d2a5cgar23scu2.cloudfront.net/static/images/redesign/actor.default.tmb.gif"}, "characters": [{"name": "Singer at Party"}]}, {"person": {"url": "/celebrity/fergus_ofarrell/", "name": "Fergus O'Farrell", "thumbnailImg": "https://d2a5cgar23scu2.cloudfront.net/static/images/redesign/actor.default.tmb.gif"}, "characters": [{"name": "Singer at Party"}]}, {"person": {"url": "/celebrity/martina_akindojctimi/", "name": "Martina Akindojctimi", "thumbnailImg": "https://d2a5cgar23scu2.cloudfront.net/static/images/redesign/actor.default.tmb.gif"}, "characters": [{"name": "Person On Stoop"}]}, {"person": {"url": "/celebrity/ruslan_mannanu/", "name": "Ruslan Mannanu", "thumbnailImg": "https://d2a5cgar23scu2.cloudfront.net/static/images/redesign/actor.default.tmb.gif"}, "characters": [{"name": "Person On Stoop"}]}, {"person": {"url": "/celebrity/francis_usanga/", "name": "Francis Usanga", "thumbnailImg": "https://d2a5cgar23scu2.cloudfront.net/static/images/redesign/actor.default.tmb.gif"}, "characters": [{"name": "Person On Stoop"}]}, {"person": {"url": "/celebrity/price_tylot_khumaho/", "name": "Price Tylot Khumaho", "thumbnailImg": "https://d2a5cgar23scu2.cloudfront.net/static/images/redesign/actor.default.tmb.gif"}, "characters": [{"name": "Person On Stoop"}]}, {"person": {"url": "/celebrity/joe_adebe/", "name": "Joe Adebe", "thumbnailImg": "https://d2a5cgar23scu2.cloudfront.net/static/images/redesign/actor.default.tmb.gif"}, "characters": [{"name": "Person On Stoop"}]}, {"person": {"url": "/celebrity/bernard_gibsenen/", "name": "Bernard Gibsenen", "thumbnailImg": "https://d2a5cgar23scu2.cloudfront.net/static/images/redesign/actor.default.tmb.gif"}, "characters": [{"name": "Shop Assistant"}]}]}, "title": "Once", "adjustedScore": 102.053755819077, "ratings": {"critics_rating": "Certified Fresh", "audience_score": 91, "dvdReleaseDate": 1197964800000, "critics_score": 97, "theaterReleaseDate": 1179471600000, "audience_rating": "Upright"}, "videoClips": {"mainTrailer": {"hlsUrl": "http://video.internetvideoarchive.net/video.m3u8?cmd=6&publishedid=242413&customerid=300120&e=1619087370216&sub=RTO&fmt=11&h=961518d00974ec853546f668ea5a96e4", "seconds": 0, "minutes": 2, "id": 10889483, "title": "Once", "thumbUrl": "http://content.internetvideoarchive.com/content/photos/1075/242413_009.jpg", "mp4Url": "http://video.internetvideoarchive.net/video.mp4?cmd=6&publishedid=242413&customerid=300120&e=1619087370216&sub=RTO&fmt=4&videokbrate=750&h=79bb61bcf64ab69bedcf477319725800"}, "size": 2, "videoClips": [{"hlsUrl": "http://video.internetvideoarchive.net/video.m3u8?cmd=6&publishedid=242413&customerid=300120&e=1619087370216&sub=RTO&fmt=11&h=961518d00974ec853546f668ea5a96e4", "seconds": 0, "minutes": 2, "id": 10889483, "title": "Once", "thumbUrl": "http://content.internetvideoarchive.com/content/photos/1075/242413_009.jpg", "mp4Url": "http://video.internetvideoarchive.net/video.mp4?cmd=6&publishedid=242413&customerid=300120&e=1619087370216&sub=RTO&fmt=4&videokbrate=750&h=79bb61bcf64ab69bedcf477319725800"}, {"hlsUrl": "http://video.internetvideoarchive.net/video.m3u8?cmd=6&publishedid=http://link.theplatform.com/s/NGweTC/media/6xmojgCp4jsh&customerid=300120&e=1619087370216&sub=RTO&fmt=11&h=7d5123579ff42e76e80bb8925195d502", "seconds": 5, "minutes": 2, "id": 11308897, "title": "Once: Trailer 1", "thumbUrl": "http://resizing.flixster.com/KDrJ_wCAANH6M2DnlkvRNnWySXQ=/171x128/v1.bjsyMDQ3NjA2O2o7MTg3ODg7MjA0ODsxMDgwOzE5MjA", "mp4Url": "http://video.internetvideoarchive.net/video.mp4?cmd=6&publishedid=http://link.theplatform.com/s/NGweTC/media/6xmojgCp4jsh&customerid=300120&e=1619087370216&sub=RTO&fmt=4&videokbrate=750&h=7072d2de6a2dd6dd1911b11132e69cc4"}]}, "isUpcoming": false, "posters": {"original": "https://resizing.flixster.com/LD8XneCY5_ca8JmbtYyCE7FvVKk=/900x1200/v1.bTsxMTIxNzA1MztqOzE4ODg3OzIwNDg7OTAwOzEyMDA", "detailed": "https://resizing.flixster.com/udhBo7Jde0_ff0TjkKf3uGBdgXE=/180x240/v1.bTsxMTIxNzA1MztqOzE4ODg3OzIwNDg7OTAwOzEyMDA", "profile": "https://resizing.flixster.com/SScM0VuPJyUm0eS7TIZmmu6492s=/120x160/v1.bTsxMTIxNzA1MztqOzE4ODg3OzIwNDg7OTAwOzEyMDA", "thumbnail": "https://resizing.flixster.com/pWJc9S3rhabknqlG20Pwy08qC4o=/54x72/v1.bTsxMTIxNzA1MztqOzE4ODg3OzIwNDg7OTAwOzEyMDA"}, "isLimited": false, "mainTrailer": {"thumbUrl": "https://content.internetvideoarchive.com/content/photos/1075/242413_009.jpg", "hlsUrl": "http://video.internetvideoarchive.net/video.m3u8?cmd=6&publishedid=242413&customerid=300120&e=1619087369625&sub=RTO&fmt=11&h=c37ddbe46e0e3eaa3209c70dc7c42b8c", "id": 10889483, "mp4Url": "http://video.internetvideoarchive.net/video.mp4?cmd=6&publishedid=242413&customerid=300120&e=1619087369625&sub=RTO&fmt=4&videokbrate=750&h=82af213ba9294fa869d447fb0b07a005"}, "advisory": "for language", "id": 528361586}